{
  "bm-only-current-color-enabled": "bm-0",
  "bm-checkbox-colors-completed": "bm-1",
  "bm-button-colors-disable-all": "bm-2",
  "bm-checkbox-colors-unlocked": "bm-3",
  "bm-button-colors-enable-all": "bm-4",
  "bm-contain-buttons-template": "bm-5",
  "bm-button-set-eventprovider": "bm-6",
  "bm-button-colors-container": "bm-7",
  "bm-download-progress-text": "bm-8",
  "bm-contain-buttons-action": "bm-9",
  "bm-event-hide-unavailable": "bm-a",
  "bm-theme-override-enabled": "bm-b",
  "bm-contain-templatefilter": "bm-c",
  "bm-rebuild-template-list": "bm-d",
  "bm-user-nextpixel-plural": "bm-e",
  "bm-memory-saving-enabled": "bm-f",
  "bm-display-coords1-copy": "bm-g",
  "bm-display-coords2-copy": "bm-h",
  "bm-progress-bar-enabled": "bm-i",
  "bm-button-refresh-event": "bm-j",
  "bm-download-coords-dim": "bm-k",
  "bm-contain-colorfilter": "bm-l",
  "bm-input-file-template": "bm-m",
  "bm-templatefilter-list": "bm-n",
  "bm-rebuild-color-list": "bm-o",
  "bm-rebuild-event-list": "bm-p",
  "bm-contain-automation": "bm-q",
  "bm-checkbox-container": "bm-r",
  "bm-event-hide-claimed": "bm-s",
  "bm-contain-eventlist": "bm-t",
  "bm-download-progress": "bm-u",
  "bm-contain-eventitem": "bm-v",
  "bm-contain-userinfo": "bm-w",
  "bm-charge-countdown": "bm-x",
  "bm-colorfilter-list": "bm-y",
  "bm-display-coords1": "bm-z",
  "bm-display-coords2": "bm-A",
  "bm-download-coords": "bm-B",
  "bm-button-teleport": "bm-C",
  "bm-template-anchor": "bm-D",
  "bm-user-nextpixel": "bm-E",
  "bm-user-nextlevel": "bm-F",
  "bm-contain-header": "bm-G",
  "bm-contain-coords": "bm-H",
  "bm-button-disable": "bm-I",
  "bm-show-error-map": "bm-J",
  "bm-eventitem-list": "bm-K",
  "bm-button-convert": "bm-L",
  "bm-button-website": "bm-M",
  "bm-user-droplets": "bm-N",
  "bm-output-status": "bm-O",
  "bm-button-coords": "bm-P",
  "bm-button-create": "bm-Q",
  "bm-button-enable": "bm-R",
  "bm-event-enabled": "bm-S",
  "bm-theme-setting": "bm-T",
  "bm-status-hidden": "bm-U",
  "bm-user-charges": "bm-V",
  "bm-charge-count": "bm-W",
  "bm-dot-template": "bm-X",
  "bm-button-paint": "bm-Y",
  "bm-button-move": "bm-Z",
  "bm-color-sort": "bm--",
  "bm-lastFetch": "bm-_",
  "bm-user-name": "bm-10",
  "bm-input-tx": "bm-11",
  "bm-input-ty": "bm-12",
  "bm-input-px": "bm-13",
  "bm-input-py": "bm-14",
  "bm-bar-drag": "bm-15",
  "bm-overlay": "bm-16",
  "bm-result": "bm-17",
  "bm-cStyle": "bm-18",
  "bm-canvas": "bm-19",
  "bm-footer": "bm-1a",
  "bm-hooked": "bm-1b",
  "bm-name": "bm-1c",
  "bm-help": "bm-1d"
}